osu/__init__.py
osu/auth.py
osu/client.py
osu/constants.py
osu/enums.py
osu/exceptions.py
osu/http.py
osu/notification.py
osu/path.py
osu/results.py
osu/scope.py
osu/util.py
osu/asyncio/__init__.py
osu/asyncio/auth.py
osu/asyncio/client.py
osu/asyncio/http.py
osu/objects/__init__.py
osu/objects/achievement.py
osu/objects/beatmap.py
osu/objects/beatmapset_event.py
osu/objects/build.py
osu/objects/chat.py
osu/objects/comment.py
osu/objects/current_user_attributes.py
osu/objects/discussion.py
osu/objects/event.py
osu/objects/forum.py
osu/objects/group.py
osu/objects/kudosu.py
osu/objects/match.py
osu/objects/multiplayer.py
osu/objects/news.py
osu/objects/notification.py
osu/objects/ranking.py
osu/objects/score.py
osu/objects/seasonal_background.py
osu/objects/user.py
osu/objects/wiki.py
osu_py-4.1.0.dist-info/LICENSE
osu_py-4.1.0.dist-info/METADATA
osu_py-4.1.0.dist-info/WHEEL
osu_py-4.1.0.dist-info/top_level.txt
osu_py-4.1.0.dist-info/RECORD
