Metadata-Version: 2.1
Name: osu.py
Version: 4.1.0
Summary: API Wrapper for osu!api v2 written in Python.
Home-page: https://github.com/Sheppsu/osu.py
Author: Sheppsu
License: MIT
Project-URL: Bug Tracker, https://github.com/Sheepposu/osu.py/issues
Project-URL: osu.py documentation, https://osupy.readthedocs.io/
Project-URL: osu!api v2 documentation, https://osu.ppy.sh/docs/index.html
Project-URL: Code examples, https://github.com/Sheepposu/osu.py/tree/main/examples
Classifier: Programming Language :: Python :: 3
Classifier: License :: OSI Approved :: MIT License
Classifier: Operating System :: OS Independent
Classifier: Natural Language :: English
Classifier: Intended Audience :: Developers
Requires-Python: >=3.8.0
License-File: LICENSE
Requires-Dist: requests<3,>=2.25.1
Provides-Extra: async
Requires-Dist: aiohttp<4,>=3.9.2; extra == "async"
Provides-Extra: notifications
Requires-Dist: websockets<14,>=13.1; extra == "notifications"
Provides-Extra: replay
Requires-Dist: osrparse<8,>=7.0.1; extra == "replay"
Provides-Extra: tests
Requires-Dist: pytest<9,>=8.3.3; extra == "tests"
Requires-Dist: pytest-asyncio<1,>=0.24.0; extra == "tests"
Requires-Dist: pytest-dependency<1,>=0.6.0; extra == "tests"
